EasyIPCLarge/MemoryClient.py
EasyIPCLarge/MemoryServer.py
EasyIPCLarge/MsgClient.py
EasyIPCLarge/MsgServer.py
EasyIPCLarge/NameConst.py
EasyIPCLarge/__init__.py
EasyIPCLarge/Msg/Msg.py
EasyIPCLarge/Msg/__init__.py
EasyIPCLarge/Msg/constants.py
EasyIPCLarge/Msg/ttypes.py
EasyIPCLarge-1.0.0.dist-info/METADATA
EasyIPCLarge-1.0.0.dist-info/WHEEL
EasyIPCLarge-1.0.0.dist-info/top_level.txt
EasyIPCLarge-1.0.0.dist-info/RECORD
