Metadata-Version: 2.1
Name: EasyIPCLarge
Version: 1.0.0
Summary: A library for high-speed transfer of large data between processes
Home-page: UNKNOWN
Author: YunWen
Author-email: yunwen@xiaobing.ai
License: MIT
Platform: UNKNOWN
Requires-Python: >= 3.8
Requires-Dist: thrift (>=0.16.0)
